fastsqs/__init__.py
fastsqs/app.py
fastsqs/concurrency.py
fastsqs/events.py
fastsqs/exceptions.py
fastsqs/presets.py
fastsqs/types.py
fastsqs/utils.py
fastsqs/concurrency/__init__.py
fastsqs/concurrency/concurrency.py
fastsqs/concurrency/decorators.py
fastsqs/logger/__init__.py
fastsqs/logger/config.py
fastsqs/logger/elasticsearch_handler.py
fastsqs/logger/logger.py
fastsqs/logger/state.py
fastsqs/logger/utils.py
fastsqs/middleware/__init__.py
fastsqs/middleware/base.py
fastsqs/middleware/error_handling.py
fastsqs/middleware/idempotency.py
fastsqs/middleware/logging.py
fastsqs/middleware/parallelization.py
fastsqs/middleware/timing.py
fastsqs/middleware/visibility.py
fastsqs/routing/__init__.py
fastsqs/routing/entry.py
fastsqs/routing/router.py
fastsqs/telemetry/__init__.py
fastsqs/telemetry/decorators.py
fastsqs/telemetry/telemetry.py
fastsqs/telemetry/services/__init__.py
fastsqs/telemetry/services/metrics.py
fastsqs/telemetry/services/tracer.py
fastsqs-0.4.4.dist-info/licenses/LICENSE
fastsqs-0.4.4.dist-info/METADATA
fastsqs-0.4.4.dist-info/WHEEL
fastsqs-0.4.4.dist-info/top_level.txt
fastsqs-0.4.4.dist-info/RECORD
