Metadata-Version: 2.4
Name: fastsqs
Version: 0.4.4
Summary: FastAPI-like, modern SQS message processing for Python with advanced features
Home-page: https://github.com/lafayettegabe/fastsqs
Author: Gabriel LaFayette
Author-email: gabriel.lafayette@proton.me
License: MIT
Keywords: sqs aws lambda serverless async fastapi pydantic message-processing
Classifier: Programming Language :: Python :: 3
Classifier: Programming Language :: Python :: 3.8
Classifier: Programming Language :: Python :: 3.9
Classifier: Programming Language :: Python :: 3.10
Classifier: Programming Language :: Python :: 3.11
Classifier: Programming Language :: Python :: 3.12
Classifier: License :: OSI Approved :: MIT License
Classifier: Operating System :: OS Independent
Classifier: Development Status :: 4 - Beta
Classifier: Intended Audience :: Developers
Classifier: Topic :: Software Development :: Libraries :: Python Modules
Classifier: Topic :: System :: Distributed Computing
Classifier: Topic :: Internet :: WWW/HTTP :: Dynamic Content
Requires-Python: >=3.8
License-File: LICENSE
Requires-Dist: pydantic>=2.0.0
Provides-Extra: dynamodb
Requires-Dist: boto3>=1.26.0; extra == "dynamodb"
Requires-Dist: aioboto3>=12.0.0; extra == "dynamodb"
Provides-Extra: idempotency
Requires-Dist: boto3>=1.26.0; extra == "idempotency"
Requires-Dist: aioboto3>=12.0.0; extra == "idempotency"
Provides-Extra: telemetry
Requires-Dist: opentelemetry-api>=1.32.1; extra == "telemetry"
Requires-Dist: opentelemetry-sdk>=1.32.1; extra == "telemetry"
Requires-Dist: opentelemetry-exporter-otlp>=1.32.1; extra == "telemetry"
Requires-Dist: opentelemetry-instrumentation>=0.53b1; extra == "telemetry"
Requires-Dist: elasticsearch>=8.11.1; extra == "telemetry"
Provides-Extra: all
Requires-Dist: boto3>=1.26.0; extra == "all"
Requires-Dist: aioboto3>=12.0.0; extra == "all"
Requires-Dist: opentelemetry-api>=1.32.1; extra == "all"
Requires-Dist: opentelemetry-sdk>=1.32.1; extra == "all"
Requires-Dist: opentelemetry-exporter-otlp>=1.32.1; extra == "all"
Requires-Dist: opentelemetry-instrumentation>=0.53b1; extra == "all"
Requires-Dist: elasticsearch>=8.11.1; extra == "all"
Dynamic: author
Dynamic: author-email
Dynamic: classifier
Dynamic: description
Dynamic: description-content-type
Dynamic: home-page
Dynamic: keywords
Dynamic: license
Dynamic: license-file
Dynamic: provides-extra
Dynamic: requires-dist
Dynamic: requires-python
Dynamic: summary
